{
    "os": "Linux-5.4.0-131-generic-x86_64-with-glibc2.27",
    "python": "3.11.11",
    "heartbeatAt": "2025-01-27T08:13:52.336569",
    "startedAt": "2025-01-27T08:13:52.016896",
    "docker": null,
    "cuda": null,
    "args": [
        "--batch_size=2048",
        "--d_layers=512",
        "--data_path=../../data/news",
        "--dataset=news",
        "--dim_t=128",
        "--dropout=0.3",
        "--log_interval=50",
        "--lr=0.01",
        "--n_layers=5",
        "--num_epochs=4000",
        "--seed=42",
        "--task_type=regression"
    ],
    "state": "running",
    "program": "/fs01/home/aguzmanc/xvfm/src/sweeps/../../main.py",
    "codePathLocal": null,
    "codePath": "main.py",
    "git": {
        "remote": "https://github.com/andresguzco/xvfm/",
        "commit": "9a3f3becedd0a9ee3e6a4b275fee025a2f336697"
    },
    "email": "andresguzco@gmail.com",
    "root": "/fs01/home/aguzmanc/xvfm",
    "host": "gpu145.cluster.local",
    "username": "aguzmanc",
    "executable": "/h/aguzmanc/miniforge3/envs/eval/bin/python3.11",
    "cpu_count": 20,
    "cpu_count_logical": 40,
    "cpu_freq": {
        "current": 1374.6867500000003,
        "min": 0.0,
        "max": 0.0
    },
    "cpu_freq_per_core": [
        {
            "current": 1000.083,
            "min": 0.0,
            "max": 0.0
        },
        {
            "current": 2884.659,
            "min": 0.0,
            "max": 0.0
        },
        {
            "current": 1314.533,
            "min": 0.0,
            "max": 0.0
        },
        {
            "current": 2897.58,
            "min": 0.0,
            "max": 0.0
        },
        {
            "current": 1000.145,
            "min": 0.0,
            "max": 0.0
        },
        {
            "current": 1000.149,
            "min": 0.0,
            "max": 0.0
        },
        {
            "current": 1000.005,
            "min": 0.0,
            "max": 0.0
        },
        {
            "current": 1000.218,
            "min": 0.0,
            "max": 0.0
        },
        {
            "current": 1000.124,
            "min": 0.0,
            "max": 0.0
        },
        {
            "current": 1000.615,
            "min": 0.0,
            "max": 0.0
        },
        {
            "current": 999.976,
            "min": 0.0,
            "max": 0.0
        },
        {
            "current": 1000.36,
            "min": 0.0,
            "max": 0.0
        },
        {
            "current": 1000.072,
            "min": 0.0,
            "max": 0.0
        },
        {
            "current": 1000.135,
            "min": 0.0,
            "max": 0.0
        },
        {
            "current": 1000.188,
            "min": 0.0,
            "max": 0.0
        },
        {
            "current": 2859.132,
            "min": 0.0,
            "max": 0.0
        },
        {
            "current": 1000.844,
            "min": 0.0,
            "max": 0.0
        },
        {
            "current": 1000.054,
            "min": 0.0,
            "max": 0.0
        },
        {
            "current": 2705.497,
            "min": 0.0,
            "max": 0.0
        },
        {
            "current": 1000.042,
            "min": 0.0,
            "max": 0.0
        },
        {
            "current": 1000.461,
            "min": 0.0,
            "max": 0.0
        },
        {
            "current": 2912.572,
            "min": 0.0,
            "max": 0.0
        },
        {
            "current": 1529.639,
            "min": 0.0,
            "max": 0.0
        },
        {
            "current": 2075.272,
            "min": 0.0,
            "max": 0.0
        },
        {
            "current": 1000.101,
            "min": 0.0,
            "max": 0.0
        },
        {
            "current": 1000.05,
            "min": 0.0,
            "max": 0.0
        },
        {
            "current": 1000.024,
            "min": 0.0,
            "max": 0.0
        },
        {
            "current": 1000.213,
            "min": 0.0,
            "max": 0.0
        },
        {
            "current": 1000.509,
            "min": 0.0,
            "max": 0.0
        },
        {
            "current": 1000.169,
            "min": 0.0,
            "max": 0.0
        },
        {
            "current": 1000.027,
            "min": 0.0,
            "max": 0.0
        },
        {
            "current": 1000.036,
            "min": 0.0,
            "max": 0.0
        },
        {
            "current": 1000.25,
            "min": 0.0,
            "max": 0.0
        },
        {
            "current": 1000.01,
            "min": 0.0,
            "max": 0.0
        },
        {
            "current": 1000.052,
            "min": 0.0,
            "max": 0.0
        },
        {
            "current": 2902.066,
            "min": 0.0,
            "max": 0.0
        },
        {
            "current": 1000.109,
            "min": 0.0,
            "max": 0.0
        },
        {
            "current": 1000.247,
            "min": 0.0,
            "max": 0.0
        },
        {
            "current": 2901.203,
            "min": 0.0,
            "max": 0.0
        },
        {
            "current": 1000.049,
            "min": 0.0,
            "max": 0.0
        }
    ],
    "disk": {
        "/": {
            "total": 819.2013664245605,
            "used": 46.14154815673828
        }
    },
    "gpu": "Quadro RTX 6000",
    "gpu_count": 1,
    "gpu_devices": [
        {
            "name": "Quadro RTX 6000",
            "memory_total": 24159191040
        }
    ],
    "memory": {
        "total": 188.58802795410156
    }
}
